zipdas/__init__.py
zipdas/data.py
zipdas/model.py
ZipDAS-0.1.1.dist-info/LICENSE
ZipDAS-0.1.1.dist-info/METADATA
ZipDAS-0.1.1.dist-info/WHEEL
ZipDAS-0.1.1.dist-info/top_level.txt
ZipDAS-0.1.1.dist-info/RECORD
