Metadata-Version: 2.1
Name: ZipDAS
Version: 0.1.1
License-File: LICENSE
Requires-Dist: numpy
Requires-Dist: h5py
Requires-Dist: matplotlib
Requires-Dist: pandas
